{
  "updated_at": "2026-06-19 22:54:48 UTC",
  "tokens": [
    {
      "mint": "v6aLjrmYxRiG3juzP5fFhehHQy9NBDgLqHbXjPupump",
      "symbol": "ASH",
      "name": "Ash",
      "market_cap": 12966.84,
      "vol_24h": 35077.15,
      "liq_usd": 0.0,
      "pattern_id": 2,
      "whale_count": 4,
      "bot_count": 11,
      "retail_count": 11,
      "sol_5min": 6.49,
      "bot_ratio": 0.423
    },
    {
      "mint": "GtrsqgwhixgCgUuXXkgSma3VaLvyRzQyFqfkdEERpump",
      "symbol": "ARC",
      "name": "ARC",
      "market_cap": 258687.0,
      "vol_24h": 1364984.36,
      "liq_usd": 39229.71,
      "pattern_id": 0,
      "whale_count": 954,
      "bot_count": 0,
      "retail_count": 11036,
      "sol_5min": 572.95,
      "bot_ratio": 0.0
    },
    {
      "mint": "9cRCn9rGT8V2imeM2BaKs13yhMEais3ruM3rPvTGpump",
      "symbol": "ANSEM",
      "name": "The Black Bull",
      "market_cap": 247212.0,
      "vol_24h": 517248.33,
      "liq_usd": 38920.49,
      "pattern_id": 5,
      "whale_count": 1,
      "bot_count": 2,
      "retail_count": 0,
      "sol_5min": 0.73,
      "bot_ratio": 0.667
    },
    {
      "mint": "GkdKLCVrRaTKNyb1JakxvfAHPKTBPdTWdXvoYvcbpump",
      "symbol": "Alpha",
      "name": "This is alpha",
      "market_cap": 15510.0,
      "vol_24h": 0.24,
      "liq_usd": 2.73,
      "pattern_id": 2,
      "whale_count": 3,
      "bot_count": 20,
      "retail_count": 4,
      "sol_5min": 1.31,
      "bot_ratio": 0.741
    },
    {
      "mint": "6trVbd265ZdvnASeimHVAWcAyCwZP8Xyy9Yykdtjpump",
      "symbol": "Mosk",
      "name": "Elun Mosk",
      "market_cap": 35282.0,
      "vol_24h": 33448.06,
      "liq_usd": 13160.16,
      "pattern_id": 6,
      "whale_count": 2,
      "bot_count": 7,
      "retail_count": 3,
      "sol_5min": 1.04,
      "bot_ratio": 0.583
    },
    {
      "mint": "7WRE3LKDCCr9sDMKH9599AXfedPsifrNZQtoZpHopump",
      "symbol": "Pumba",
      "name": "Pumba",
      "market_cap": 2026.26,
      "vol_24h": 32349.35,
      "liq_usd": 0.0,
      "pattern_id": 4,
      "whale_count": 0,
      "bot_count": 0,
      "retail_count": 0,
      "sol_5min": 0.0,
      "bot_ratio": 0.0
    },
    {
      "mint": "H86Mm1QWCW5XrA4TQaQcCLfwG8u1xjQ2RupigorYpump",
      "symbol": "Elon",
      "name": "The White Bull",
      "market_cap": 13358.0,
      "vol_24h": 24785.48,
      "liq_usd": 8364.27,
      "pattern_id": 6,
      "whale_count": 2,
      "bot_count": 8,
      "retail_count": 4,
      "sol_5min": 0.68,
      "bot_ratio": 0.571
    },
    {
      "mint": "268NzgMSJPvvGVuExa9rdmeS88TZBP66gbAE7UCppump",
      "symbol": "STRETCHGPT",
      "name": "STRC",
      "market_cap": 28948.0,
      "vol_24h": 26845.17,
      "liq_usd": 11926.29,
      "pattern_id": 6,
      "whale_count": 0,
      "bot_count": 1,
      "retail_count": 2,
      "sol_5min": 0.0,
      "bot_ratio": 0.333
    },
    {
      "mint": "53eo9Q6J4WCxS5cVC3hVXYv5vSNuqt3ofWejt3ppump",
      "symbol": "44BLK",
      "name": "BarrackBlock",
      "market_cap": 2412.33,
      "vol_24h": 11643.15,
      "liq_usd": 0.0,
      "pattern_id": 6,
      "whale_count": 1,
      "bot_count": 11,
      "retail_count": 7,
      "sol_5min": 1.21,
      "bot_ratio": 0.579
    },
    {
      "mint": "2pL9J9mTD9RAGS9jnNeB2kKR62ar8pnQAV2sMgyrpump",
      "symbol": "WASABICRAFT",
      "name": "WASABICRAFT",
      "market_cap": 465227.0,
      "vol_24h": 1549646.13,
      "liq_usd": 51849.95,
      "pattern_id": 6,
      "whale_count": 1,
      "bot_count": 3,
      "retail_count": 1,
      "sol_5min": 0.51,
      "bot_ratio": 0.6
    },
    {
      "mint": "32sVv8B8TXtjquXbMoN2M9AawVkrbathGFqGxC5mpump",
      "symbol": "DMN",
      "name": "Diamond Coin",
      "market_cap": 7206.0,
      "vol_24h": 33955.62,
      "liq_usd": 5953.83,
      "pattern_id": 4,
      "whale_count": 1,
      "bot_count": 0,
      "retail_count": 0,
      "sol_5min": 0.87,
      "bot_ratio": 0.0
    },
    {
      "mint": "H4chsqkobEKjjiAt7r3TLJvp7qprR6aasjJFtkQcAqun",
      "symbol": "SKI",
      "name": "Ski Mask Dog",
      "market_cap": 38269.0,
      "vol_24h": 159183.82,
      "liq_usd": 14652.89,
      "pattern_id": 4,
      "whale_count": 1,
      "bot_count": 0,
      "retail_count": 7,
      "sol_5min": 0.85,
      "bot_ratio": 0.0
    },
    {
      "mint": "qxfUTZkfrP3pEmxhAdYyQYRUcGi63zv1gA4z9RbBzr3",
      "symbol": "Dad",
      "name": "Happy fathers day",
      "market_cap": 25866.0,
      "vol_24h": 4299.47,
      "liq_usd": 11262.85,
      "pattern_id": 4,
      "whale_count": 0,
      "bot_count": 0,
      "retail_count": 18,
      "sol_5min": 0.0,
      "bot_ratio": 0.0
    },
    {
      "mint": "qYc4gQ9xVq48XmeBBUh7GMfTYycoLS1m3VTT9tapump",
      "symbol": "RUMBLE",
      "name": "Realm Rumble",
      "market_cap": 197696.0,
      "vol_24h": 386447.77,
      "liq_usd": 33106.72,
      "pattern_id": 0,
      "whale_count": 26,
      "bot_count": 0,
      "retail_count": 267,
      "sol_5min": 16.01,
      "bot_ratio": 0.0
    },
    {
      "mint": "D3goe7QkDWcDHV9ib1tkVz7kMmzCQtzwG5QZqtgmpump",
      "symbol": "CHART",
      "name": "CHART CAT OFFICIAL",
      "market_cap": 17630.0,
      "vol_24h": 133.94,
      "liq_usd": 10052.93,
      "pattern_id": 6,
      "whale_count": 2,
      "bot_count": 14,
      "retail_count": 5,
      "sol_5min": 1.1,
      "bot_ratio": 0.667
    },
    {
      "mint": "CPYrgdAYWFQD74ZtsR8mEBWW7qnrXnegcn7gDMobpump",
      "symbol": "CHIKI",
      "name": "CHIKI MONSTERS",
      "market_cap": 98236.0,
      "vol_24h": 620190.75,
      "liq_usd": 32406.57,
      "pattern_id": 6,
      "whale_count": 2,
      "bot_count": 1,
      "retail_count": 2,
      "sol_5min": 2.66,
      "bot_ratio": 0.2
    },
    {
      "mint": "GTaviCd65VP3EDVwUG17yE2ATP7LHiBHEsLiyTzRpj6R",
      "symbol": "GTAVI",
      "name": "Grand Theft Auto VI",
      "market_cap": 20750.0,
      "vol_24h": 30182.13,
      "liq_usd": 10077.79,
      "pattern_id": 6,
      "whale_count": 2,
      "bot_count": 2,
      "retail_count": 10,
      "sol_5min": 2.76,
      "bot_ratio": 0.143
    },
    {
      "mint": "GW637WykoW4cnzKsyxSUhHEZQLU5Vq9ev7d5kdzYpump",
      "symbol": "OBI",
      "name": "OBI",
      "market_cap": 1268654.0,
      "vol_24h": 115630.16,
      "liq_usd": 80297.23,
      "pattern_id": 6,
      "whale_count": 2,
      "bot_count": 4,
      "retail_count": 5,
      "sol_5min": 1.97,
      "bot_ratio": 0.364
    },
    {
      "mint": "J4ozfGVtuDYYkWFpCV5n8LYZXpBp8hcpaXJcPeNDpump",
      "symbol": "chic",
      "name": "chic",
      "market_cap": 50589.0,
      "vol_24h": 77975.58,
      "liq_usd": 17655.08,
      "pattern_id": 4,
      "whale_count": 0,
      "bot_count": 0,
      "retail_count": 15,
      "sol_5min": 0.51,
      "bot_ratio": 0.0
    },
    {
      "mint": "8QAfLaNuyZhwg4LMomfe8CKX7XwYwSiGQDPUivkppump",
      "symbol": "MFGA",
      "name": "Make Farmers Great Again",
      "market_cap": 16644.0,
      "vol_24h": 723321.43,
      "liq_usd": 9396.85,
      "pattern_id": 1,
      "whale_count": 0,
      "bot_count": 1,
      "retail_count": 0,
      "sol_5min": 0.0,
      "bot_ratio": 1.0
    },
    {
      "mint": "BmNASdTTgXc1AhvMqFiPBKp3kwrPeHchn7LbbWeSpump",
      "symbol": "COLLECTABLE",
      "name": "Collectable Coin",
      "market_cap": 137100.0,
      "vol_24h": 668841.52,
      "liq_usd": 28080.15,
      "pattern_id": 0,
      "whale_count": 25,
      "bot_count": 0,
      "retail_count": 276,
      "sol_5min": 15.28,
      "bot_ratio": 0.0
    },
    {
      "mint": "A7FYD3854T23r3dfNFtW9bFNjVN4kihodpSznQSnpump",
      "symbol": "HARRIUT",
      "name": "HARRIUT TUBMUN",
      "market_cap": 2903.0,
      "vol_24h": 117940.22,
      "liq_usd": 3881.42,
      "pattern_id": 4,
      "whale_count": 0,
      "bot_count": 0,
      "retail_count": 31,
      "sol_5min": 0.12,
      "bot_ratio": 0.0
    },
    {
      "mint": "E8UXwqhNiiMwVRRV4F81rUBUYXNUd4bA78ZxpQxZpump",
      "symbol": "JAMESON",
      "name": "Justice For Jameson The Doodle",
      "market_cap": 110261.0,
      "vol_24h": 298629.19,
      "liq_usd": 27636.85,
      "pattern_id": 2,
      "whale_count": 3,
      "bot_count": 8,
      "retail_count": 6,
      "sol_5min": 9.81,
      "bot_ratio": 0.471
    },
    {
      "mint": "4GdrUM7WnxyrQhbX8RKUX2Juy7azs1Lw94mcp4bvpump",
      "symbol": "DXED",
      "name": "DXED",
      "market_cap": 8468.98,
      "vol_24h": 72910.78,
      "liq_usd": 0.0,
      "pattern_id": 2,
      "whale_count": 4,
      "bot_count": 9,
      "retail_count": 11,
      "sol_5min": 4.9,
      "bot_ratio": 0.375
    },
    {
      "mint": "3NMQuwg7WGqzqjqwUnR3Ciwo3AoVE39yYQnTqK49pump",
      "symbol": "TRENCHES",
      "name": "Trenches Tokens",
      "market_cap": 94396.0,
      "vol_24h": 683669.01,
      "liq_usd": 24221.98,
      "pattern_id": 4,
      "whale_count": 0,
      "bot_count": 0,
      "retail_count": 2,
      "sol_5min": 0.0,
      "bot_ratio": 0.0
    },
    {
      "mint": "riftZuJ53bRDbZGHfrE2emYroB7sFUYaUKtUdTjL7BS",
      "symbol": "RIFT",
      "name": "Rift Raiders",
      "market_cap": 11566.0,
      "vol_24h": 37245.89,
      "liq_usd": 7556.94,
      "pattern_id": 6,
      "whale_count": 2,
      "bot_count": 3,
      "retail_count": 34,
      "sol_5min": 1.73,
      "bot_ratio": 0.077
    },
    {
      "mint": "4LKj2h5V9tdYTpvaUfQtEXrKNYXymDDXNeZjGG75pump",
      "symbol": "MAZE",
      "name": "MAZE BANK",
      "market_cap": 10920.9,
      "vol_24h": 53110.11,
      "liq_usd": 0.0,
      "pattern_id": 2,
      "whale_count": 3,
      "bot_count": 0,
      "retail_count": 148,
      "sol_5min": 2.27,
      "bot_ratio": 0.0
    },
    {
      "mint": "6qjpPDW4VfiHYxmYMf8YarW1SbsLyfj1og87gycEpump",
      "symbol": "LEON",
      "name": "Leon mesk",
      "market_cap": 74806.0,
      "vol_24h": 934243.6,
      "liq_usd": 20944.72,
      "pattern_id": 2,
      "whale_count": 3,
      "bot_count": 8,
      "retail_count": 6,
      "sol_5min": 1.65,
      "bot_ratio": 0.471
    },
    {
      "mint": "CzhwdcVbSCWTdRdTta2o8LGNzWjM4QeugHG3h2iXpump",
      "symbol": "WILLOW",
      "name": "The Chonky Beaver",
      "market_cap": 2576.92,
      "vol_24h": 24025.16,
      "liq_usd": 0.0,
      "pattern_id": 4,
      "whale_count": 0,
      "bot_count": 2,
      "retail_count": 8,
      "sol_5min": 0.0,
      "bot_ratio": 0.2
    },
    {
      "mint": "9qGr59BGsWjQ3RxH3rHoSfLbLJB8abBKcE3jv4owpump",
      "symbol": "ERNEST",
      "name": "ERNEST",
      "market_cap": 7381.0,
      "vol_24h": 5.6,
      "liq_usd": 2.41,
      "pattern_id": 5,
      "whale_count": 1,
      "bot_count": 5,
      "retail_count": 1,
      "sol_5min": 0.68,
      "bot_ratio": 0.714
    },
    {
      "mint": "CBBSgHbx7spfRZ9UcsLCofGuJyWKcUsE5EMpPhxppump",
      "symbol": "Libby",
      "name": "Nietzschean Retriever",
      "market_cap": 5073.0,
      "vol_24h": 2.41,
      "liq_usd": 1.19,
      "pattern_id": 4,
      "whale_count": 0,
      "bot_count": 0,
      "retail_count": 0,
      "sol_5min": 0.0,
      "bot_ratio": 0.0
    },
    {
      "mint": "9EgrNJ3q44SUmniqLhspdoPFRp3FaQ5yor8mooq7pump",
      "symbol": "WILLOW",
      "name": "The Chonky Beaver",
      "market_cap": 4878.69,
      "vol_24h": 77246.51,
      "liq_usd": 0.0,
      "pattern_id": 6,
      "whale_count": 1,
      "bot_count": 2,
      "retail_count": 3,
      "sol_5min": 1.48,
      "bot_ratio": 0.333
    },
    {
      "mint": "2keNddbkCXnp6AraFLuC5RwLjWRQSQZrCiy22gd7pump",
      "symbol": "TREMP",
      "name": "Official Tremp",
      "market_cap": 6447.0,
      "vol_24h": 135705.85,
      "liq_usd": 5683.32,
      "pattern_id": 0,
      "whale_count": 9,
      "bot_count": 0,
      "retail_count": 337,
      "sol_5min": 5.59,
      "bot_ratio": 0.0
    },
    {
      "mint": "8BRNhhxyusRDo3UH4uKQ2GzcGm22VLmQu4eeEJJrpump",
      "symbol": "KITTY",
      "name": "First Digital Cat (1968)",
      "market_cap": 11337.0,
      "vol_24h": 0.25,
      "liq_usd": 0.03,
      "pattern_id": 4,
      "whale_count": 0,
      "bot_count": 0,
      "retail_count": 0,
      "sol_5min": 0.0,
      "bot_ratio": 0.0
    },
    {
      "mint": "RUNKtAtkQfrA23ovwn3WVEVFjmqw6hqhXTADUAsnew5",
      "symbol": "RUN",
      "name": "Endless Pumper",
      "market_cap": 3684.37,
      "vol_24h": 20623.8,
      "liq_usd": 0.0,
      "pattern_id": 4,
      "whale_count": 0,
      "bot_count": 0,
      "retail_count": 61,
      "sol_5min": 0.0,
      "bot_ratio": 0.0
    },
    {
      "mint": "5M5yNMXUpVAgYZN9mV1jHPn61EaHPaYE5iy3ZhFKJJed",
      "symbol": "PEACE",
      "name": "Peace Token",
      "market_cap": 3769993.0,
      "vol_24h": 2837393.13,
      "liq_usd": 298096.65,
      "pattern_id": 0,
      "whale_count": 24,
      "bot_count": 0,
      "retail_count": 542,
      "sol_5min": 14.88,
      "bot_ratio": 0.0
    },
    {
      "mint": "6JzX2kA9kFfrXFENP1orcqYzxpWV1Jux14Vif8ezpump",
      "symbol": "Peuce",
      "name": "Peuce Tuken",
      "market_cap": 5822.0,
      "vol_24h": 56680.07,
      "liq_usd": 5338.68,
      "pattern_id": 2,
      "whale_count": 3,
      "bot_count": 17,
      "retail_count": 6,
      "sol_5min": 2.04,
      "bot_ratio": 0.654
    },
    {
      "mint": "4xwgrb6yvue78ZCMCQsKc3XfWF8xqKkXzaKLaWw5pump",
      "symbol": "Optimist",
      "name": "The Optimist",
      "market_cap": 2688.49,
      "vol_24h": 47473.58,
      "liq_usd": 0.0,
      "pattern_id": 4,
      "whale_count": 0,
      "bot_count": 0,
      "retail_count": 274,
      "sol_5min": 0.0,
      "bot_ratio": 0.0
    },
    {
      "mint": "BPigDGX8nt3gEQgZ8dQHcVQwf7TJV1wek79jkLvypump",
      "symbol": "JACK",
      "name": "Jackies Roll",
      "market_cap": 1883.0,
      "vol_24h": 24753.45,
      "liq_usd": 3032.35,
      "pattern_id": 6,
      "whale_count": 2,
      "bot_count": 8,
      "retail_count": 3,
      "sol_5min": 0.97,
      "bot_ratio": 0.615
    },
    {
      "mint": "DKvic1v7g24Y5qLvN5XotJGYCoYuSFBamt8jzzoHpump",
      "symbol": "NIGHT",
      "name": "Night City",
      "market_cap": 16557.21,
      "vol_24h": 33514.41,
      "liq_usd": 0.0,
      "pattern_id": 6,
      "whale_count": 0,
      "bot_count": 1,
      "retail_count": 1,
      "sol_5min": 0.0,
      "bot_ratio": 0.5
    },
    {
      "mint": "F8kdUopx2htyG5khQdr7rMAsMhsFGXpgRaZm6gbepump",
      "symbol": "Jasmine",
      "name": "Jasmine Begalinova",
      "market_cap": 36883.0,
      "vol_24h": 27458.04,
      "liq_usd": 13453.21,
      "pattern_id": 2,
      "whale_count": 5,
      "bot_count": 14,
      "retail_count": 2,
      "sol_5min": 2.46,
      "bot_ratio": 0.667
    },
    {
      "mint": "F6VFdgCPdiZWoS4FJrYtyBoQjNAQ8rkfRLATViPKpump",
      "symbol": "RICH",
      "name": "Get Rich Quick",
      "market_cap": 7626.0,
      "vol_24h": 44544.7,
      "liq_usd": 6111.99,
      "pattern_id": 5,
      "whale_count": 1,
      "bot_count": 4,
      "retail_count": 1,
      "sol_5min": 0.99,
      "bot_ratio": 0.667
    },
    {
      "mint": "8KeiqwrfdEuMqwL4yqZrrcbE8jaLLUuYwqDVZVzppump",
      "symbol": "Totes",
      "name": "Trader Joe's Tote Bags",
      "market_cap": 20570.0,
      "vol_24h": 38911.74,
      "liq_usd": 10027.41,
      "pattern_id": 0,
      "whale_count": 98,
      "bot_count": 47,
      "retail_count": 752,
      "sol_5min": 58.81,
      "bot_ratio": 0.052
    },
    {
      "mint": "BZZPTgxpxVrFmK1AZhgpmpi5cNytAx7qmMcMXR2pump",
      "symbol": "TOTEBAG",
      "name": "2.99$ tote bag ",
      "market_cap": 12604.0,
      "vol_24h": 43849.79,
      "liq_usd": 7850.32,
      "pattern_id": 6,
      "whale_count": 2,
      "bot_count": 6,
      "retail_count": 0,
      "sol_5min": 1.57,
      "bot_ratio": 0.75
    },
    {
      "mint": "8wQ1N3qFW8m4wMjEYAW4TTCtdjLDAkDfFHHhLTgnnPNL",
      "symbol": "COMPETITION",
      "name": "Pump Fun Trading Competition",
      "market_cap": 2691.43,
      "vol_24h": 27096.55,
      "liq_usd": 0.0,
      "pattern_id": 6,
      "whale_count": 2,
      "bot_count": 0,
      "retail_count": 556,
      "sol_5min": 1.75,
      "bot_ratio": 0.0
    },
    {
      "mint": "GrFTi2rzDU27aasCjMGfKGwP4fdw4UErS21XhTPDpump",
      "symbol": "BALD",
      "name": "The Patriotic Eagle",
      "market_cap": 5056.02,
      "vol_24h": 77567.96,
      "liq_usd": 0.0,
      "pattern_id": 2,
      "whale_count": 3,
      "bot_count": 10,
      "retail_count": 5,
      "sol_5min": 1.23,
      "bot_ratio": 0.556
    },
    {
      "mint": "9P9qL9FsnqaH24RBbYmNPgHSYSVst8aydq4utRBApump",
      "symbol": "CROAK",
      "name": "Croak City",
      "market_cap": 4489.0,
      "vol_24h": 40487.13,
      "liq_usd": 4684.39,
      "pattern_id": 0,
      "whale_count": 9,
      "bot_count": 0,
      "retail_count": 744,
      "sol_5min": 5.51,
      "bot_ratio": 0.0
    },
    {
      "mint": "7tE4o8LymgpTApmcT2TUSud72T8pckv1riMBWMCpump",
      "symbol": "bearish",
      "name": "bearwiffish",
      "market_cap": 2712.76,
      "vol_24h": 52333.19,
      "liq_usd": 0.0,
      "pattern_id": 4,
      "whale_count": 0,
      "bot_count": 0,
      "retail_count": 1260,
      "sol_5min": 0.18,
      "bot_ratio": 0.0
    },
    {
      "mint": "CKbEiYzGRxDe9Ecg1xxXhxNcAUY3BCmj2fyhA8qHpump",
      "symbol": "zer0",
      "name": "zer0",
      "market_cap": 18529.93,
      "vol_24h": 67827.69,
      "liq_usd": 0.0,
      "pattern_id": 0,
      "whale_count": 6,
      "bot_count": 19,
      "retail_count": 9,
      "sol_5min": 7.36,
      "bot_ratio": 0.559
    },
    {
      "mint": "GNDL81hHQ4wkZbEC7kL5ymu2fbjfc5dbzg2kFXvYcPfk",
      "symbol": "Gondola",
      "name": "Gondola",
      "market_cap": 14015.75,
      "vol_24h": 47302.05,
      "liq_usd": 0.0,
      "pattern_id": 2,
      "whale_count": 7,
      "bot_count": 30,
      "retail_count": 5,
      "sol_5min": 5.52,
      "bot_ratio": 0.714
    },
    {
      "mint": "BSsD7o8pm8pdUm4VfAsrrH5Z9qfKJDbkW8mAVb1Fpump",
      "symbol": "TARTAN",
      "name": "Tartan Army",
      "market_cap": 9250.82,
      "vol_24h": 12527.11,
      "liq_usd": 0.0,
      "pattern_id": 4,
      "whale_count": 1,
      "bot_count": 2,
      "retail_count": 4,
      "sol_5min": 1.29,
      "bot_ratio": 0.286
    }
  ],
  "patterns": {
    "BALEIA_FORTE": 8,
    "BOT_SWARM": 1,
    "LENTO_WHALE": 10,
    "ORGANIC": 14,
    "RUG_CAND": 3,
    "MISTO": 15
  },
  "wallets": [
    {
      "wallet": "ACCT_21_E8UXwqhN",
      "role": "whale",
      "tokens": 1,
      "total_sol": 6.774
    },
    {
      "wallet": "Ccwg4GgUdKfPj73ttyf6YLBq8UxxDtP7WZXhsNvNeWNk",
      "role": "whale",
      "tokens": 1,
      "total_sol": 5.6454
    },
    {
      "wallet": "AdJR4GwM8497m6hDzVwC5GtbgAUS3GbJpVk88nDhjMQh",
      "role": "whale",
      "tokens": 1,
      "total_sol": 5.4082
    },
    {
      "wallet": "A5UuSxRQTeref4tYpE4KMHjnaXSMEYh67o5bmAqVmrZX",
      "role": "whale",
      "tokens": 1,
      "total_sol": 5.1165
    },
    {
      "wallet": "3sXCLhYi6QTcUhJQEsXcqtq5iLPTpUBvjisZuSaSXJz4",
      "role": "whale",
      "tokens": 1,
      "total_sol": 2.761
    },
    {
      "wallet": "FjffYKwkL4ffpxrSBci9rEVqueqJNhkLLXiUUAZWuUB7",
      "role": "whale",
      "tokens": 1,
      "total_sol": 2.3338
    },
    {
      "wallet": "ETGtjQdcMzxB51JPDamNAVgLZSFZsSVPz3z6Pk6zDYWA",
      "role": "whale",
      "tokens": 1,
      "total_sol": 1.9844
    },
    {
      "wallet": "53TJwHmTuNWkXgto95xrpZN7HzfBbFTXpvCXausWxqxo",
      "role": "whale",
      "tokens": 1,
      "total_sol": 1.9662
    },
    {
      "wallet": "ACCT_29_CPYrgdAY",
      "role": "whale",
      "tokens": 1,
      "total_sol": 1.6959
    },
    {
      "wallet": "Gy32zZnbFZ6NjyPVCyMth9ersKF5ujtZCfjQ6BFuiadk",
      "role": "whale",
      "tokens": 1,
      "total_sol": 1.4815
    },
    {
      "wallet": "EY8eY7MZGGDW3pFwmzzunSyje1byGkc2fGBUuCv46UpL",
      "role": "whale",
      "tokens": 1,
      "total_sol": 1.3546
    },
    {
      "wallet": "CpvMwgZv8qKrHopPSkZUEpFJofKBUE4LsdTJXGAjNaeW",
      "role": "whale",
      "tokens": 1,
      "total_sol": 1.2915
    },
    {
      "wallet": "3hrRZDwjyv45xWvHUsWKkVurSTVpLc4hELWDo8MNv31p",
      "role": "whale",
      "tokens": 1,
      "total_sol": 1.2138
    },
    {
      "wallet": "DobT62LjYXSU8E2vZEUosFQEXhBNQg81PQobkvsCv747",
      "role": "whale",
      "tokens": 1,
      "total_sol": 1.1757
    },
    {
      "wallet": "9QJEGxCL9jWMzfSB3yvBqY3eyG27kgVEQJKfsno7rSCc",
      "role": "whale",
      "tokens": 1,
      "total_sol": 1.1602
    },
    {
      "wallet": "Hd9cUvNqbqzagVeJqwMq1UmMTs1iVbLsUbo4gXTx18by",
      "role": "whale",
      "tokens": 1,
      "total_sol": 1.0788
    },
    {
      "wallet": "4EZmGdY7X7dtTSBgq7U2FaiiXh1x1hpMx6aMjv7ChJdC",
      "role": "whale",
      "tokens": 1,
      "total_sol": 1.0516
    },
    {
      "wallet": "GXkV7KVqWMUBMVLDVkAxTDwNbFJuH8U1cqb8bixnz9sn",
      "role": "whale",
      "tokens": 1,
      "total_sol": 0.9879
    },
    {
      "wallet": "Ad68FE9xpc2vQ8nNK3hNzWm3hQfbYUmWiwiFNnqHvWuv",
      "role": "whale",
      "tokens": 1,
      "total_sol": 0.9841
    },
    {
      "wallet": "ACCT_22_BPigDGX8",
      "role": "whale",
      "tokens": 1,
      "total_sol": 0.9688000000000001
    },
    {
      "wallet": "ACCT_26_CPYrgdAY",
      "role": "whale",
      "tokens": 1,
      "total_sol": 0.9627
    },
    {
      "wallet": "7NRddrY2Y6XM6rvq56RVDaymCVU8a2QZmKvhLaFkqySJ",
      "role": "whale",
      "tokens": 1,
      "total_sol": 0.9082
    },
    {
      "wallet": "AnonH2TuipeipbvvVYGCmaJCvkddAiLZZoNAa5u1aELh",
      "role": "whale",
      "tokens": 1,
      "total_sol": 0.8796
    },
    {
      "wallet": "4U9s6ktkZVD6W9K5X1RRVG89Mm9ZGznrPhhPhXezNedm",
      "role": "whale",
      "tokens": 1,
      "total_sol": 0.7318
    },
    {
      "wallet": "ACCT_19_9cRCn9rG",
      "role": "whale",
      "tokens": 1,
      "total_sol": 0.7271
    },
    {
      "wallet": "ACCT_15_6qjpPDW4",
      "role": "whale",
      "tokens": 1,
      "total_sol": 0.7103
    },
    {
      "wallet": "DbEh3Yah8wPtRNpcxtixHMP8Kw1H2wvfv9D1DLVH2zKH",
      "role": "whale",
      "tokens": 1,
      "total_sol": 0.6768
    },
    {
      "wallet": "ACCT_20_D3goe7Qk",
      "role": "whale",
      "tokens": 1,
      "total_sol": 0.5693
    },
    {
      "wallet": "Em1PPB1DuZiaF7oLGEx5PdxdmXPqkt8KShRXr5FRMh2a",
      "role": "whale",
      "tokens": 1,
      "total_sol": 0.5494
    },
    {
      "wallet": "ACCT_22_D3goe7Qk",
      "role": "whale",
      "tokens": 1,
      "total_sol": 0.5348
    },
    {
      "wallet": "ArnYmUrp2gdD2kYjxVb16fkufwYoH3Gei6QCY6yRNa3t",
      "role": "whale",
      "tokens": 1,
      "total_sol": 0.5129
    },
    {
      "wallet": "ACCT_13_F8kdUopx",
      "role": "whale",
      "tokens": 1,
      "total_sol": 0.5004
    },
    {
      "wallet": "ACCT_14_F8kdUopx",
      "role": "whale",
      "tokens": 1,
      "total_sol": 0.4998
    },
    {
      "wallet": "AxQ9rWNPUjeyBwdTjJshXcDSih42jE9bzviVHWZwd1dw",
      "role": "whale",
      "tokens": 1,
      "total_sol": 0.4951
    },
    {
      "wallet": "A5feDqFf1CLdZmVnq6kVbqEPVtVuNFnH9kycfU2z3fm3",
      "role": "whale",
      "tokens": 1,
      "total_sol": 0.4927
    },
    {
      "wallet": "9gKrMdo3zgZmZeBuXKC56X7BhGWThMXXTFwa5my77zJ8",
      "role": "whale",
      "tokens": 1,
      "total_sol": 0.4914
    },
    {
      "wallet": "FC9PU3KzgvLw5duSwrxPgKvGs6nqYZss7AVPZE3H5mxB",
      "role": "whale",
      "tokens": 1,
      "total_sol": 0.4901
    },
    {
      "wallet": "33tdD9NKeaaMxj52coRK15Qndrfc8M9Eqbxyn2tVEgcG",
      "role": "whale",
      "tokens": 1,
      "total_sol": 0.4839
    },
    {
      "wallet": "6Eif4N2q8fDjt7vAff1zpNNiiiUzuCAA6kno8rTYUuFS",
      "role": "whale",
      "tokens": 1,
      "total_sol": 0.483
    },
    {
      "wallet": "BR1ADA9rFxqZ76AJibayP8QeVBqsdupYJNbiEKHZkEfD",
      "role": "whale",
      "tokens": 1,
      "total_sol": 0.4474
    },
    {
      "wallet": "8HsURP9tZsGUqopEY3uxpXgbMCBFpd8nszgwPEWeQTBY",
      "role": "retail",
      "tokens": 1,
      "total_sol": 0.4349
    },
    {
      "wallet": "8HsURP9tZsGUqopEY3uxpXgbMCBFpd8nszgwPEWeQTBY",
      "role": "whale",
      "tokens": 1,
      "total_sol": 0.4322
    },
    {
      "wallet": "5UfmsRCbsKepEx19Z7m5gEAmMexMU6hA87wgoJM2i1xU",
      "role": "whale",
      "tokens": 1,
      "total_sol": 0.4315
    },
    {
      "wallet": "BggnH7CGFp4XaWcYaxEt25rBAa2r7vnZ5NLQhXbk142Q",
      "role": "whale",
      "tokens": 1,
      "total_sol": 0.4156
    },
    {
      "wallet": "5Vo7D1gpi3JoGXUQTxEyjBtzfj2zAxkcPNmee8UaecVj",
      "role": "whale",
      "tokens": 1,
      "total_sol": 0.4035
    },
    {
      "wallet": "9gKrMdo3zgZmZeBuXKC56X7BhGWThMXXTFwa5my77zJ8",
      "role": "retail",
      "tokens": 1,
      "total_sol": 0.4025
    },
    {
      "wallet": "CFyjFoX995PcpiqgtHgaJTZNjAXL3f6ZNeZPNhdcgoCY",
      "role": "whale",
      "tokens": 1,
      "total_sol": 0.4017
    },
    {
      "wallet": "F9oqdWPud5LY3EQ4e2GSGt9AVUYZsjGY216CuKaZWRcU",
      "role": "whale",
      "tokens": 1,
      "total_sol": 0.3928
    },
    {
      "wallet": "7i2D94jtQkjgMWQ32C7zXiSj6sVTH5uSNSfiC7Rkiksq",
      "role": "retail",
      "tokens": 1,
      "total_sol": 0.38930000000000003
    },
    {
      "wallet": "ACCT_14_H86Mm1QW",
      "role": "whale",
      "tokens": 1,
      "total_sol": 0.38
    }
  ],
  "sim": {
    "total_trades": 18,
    "trades": 18,
    "wins": 6,
    "losses": 12,
    "pnl_sol": 2.90166,
    "entry_sol": 10.0,
    "last_trades": [
      {
        "symbol": "MechaWar",
        "mint": "DAE2ugmx3GsZbM6RMvvVjm1Z2QmwguDDMCDpsVVbpump",
        "entry": 1.957e-05,
        "exit": 1.643e-05,
        "pnl_pct": -16.04,
        "pnl_sol": -1.6045,
        "exit_reason": "SL",
        "hold_min": 8.5,
        "ts": 1781879405
      },
      {
        "symbol": "CRAFT",
        "mint": "79Jx4SNyuzwitVxrGoCbNLuLVUNGHsQQaiswXapMpump",
        "entry": 5.734e-05,
        "exit": 2.667e-05,
        "pnl_pct": -53.49,
        "pnl_sol": -5.3488,
        "exit_reason": "SL",
        "hold_min": 117.0,
        "ts": 1781887251
      },
      {
        "symbol": "CEX",
        "mint": "EoHKjiNy8w2ZcizdGexxsHcTHvDZT44HVGJg7eDUpump",
        "entry": 6.247e-06,
        "exit": 5.355e-06,
        "pnl_pct": -14.28,
        "pnl_sol": -1.42789,
        "exit_reason": "SL",
        "hold_min": 2.6,
        "ts": 1781887403
      },
      {
        "symbol": "MFGA",
        "mint": "8QAfLaNuyZhwg4LMomfe8CKX7XwYwSiGQDPUivkppump",
        "entry": 0.0002944,
        "exit": 0.00032,
        "pnl_pct": 8.7,
        "pnl_sol": 0.86957,
        "exit_reason": "TEMPO",
        "hold_min": 12.1,
        "ts": 1781887971
      },
      {
        "symbol": "TREMP",
        "mint": "HoHtLm7M6G25u1zwKHMLL5dJbDkMqP3awLH9ULjRpump",
        "entry": 0.0001008,
        "exit": 8.754e-05,
        "pnl_pct": -13.15,
        "pnl_sol": -1.31548,
        "exit_reason": "SL",
        "hold_min": 0.2,
        "ts": 1781888171
      },
      {
        "symbol": "Totes",
        "mint": "8KeiqwrfdEuMqwL4yqZrrcbE8jaLLUuYwqDVZVzppump",
        "entry": 2.056e-05,
        "exit": 2.632e-05,
        "pnl_pct": 28.02,
        "pnl_sol": 0.28016,
        "exit_reason": "TP",
        "hold_min": 1.5,
        "ts": 1781907978
      },
      {
        "symbol": "Mosk",
        "mint": "6trVbd265ZdvnASeimHVAWcAyCwZP8Xyy9Yykdtjpump",
        "entry": 3.865e-05,
        "exit": 3.528e-05,
        "pnl_pct": -8.72,
        "pnl_sol": -0.08719,
        "exit_reason": "SL",
        "hold_min": 0.7,
        "ts": 1781908429
      },
      {
        "symbol": "TOTEBAG",
        "mint": "BZZPTgxpxVrFmK1AZhgpmpi5cNytAx7qmMcMXR2pump",
        "entry": 5.764e-06,
        "exit": 5.042e-06,
        "pnl_pct": -12.53,
        "pnl_sol": -0.12526,
        "exit_reason": "SL",
        "hold_min": 0.7,
        "ts": 1781908835
      },
      {
        "symbol": "Totes",
        "mint": "8KeiqwrfdEuMqwL4yqZrrcbE8jaLLUuYwqDVZVzppump",
        "entry": 2.551e-05,
        "exit": 2.296e-05,
        "pnl_pct": -10.0,
        "pnl_sol": -0.09996,
        "exit_reason": "SL",
        "hold_min": 1.9,
        "ts": 1781908911
      },
      {
        "symbol": "zer0",
        "mint": "CKbEiYzGRxDe9Ecg1xxXhxNcAUY3BCmj2fyhA8qHpump",
        "entry": 4.688e-05,
        "exit": 4.007e-05,
        "pnl_pct": -14.53,
        "pnl_sol": -0.14526,
        "exit_reason": "SL",
        "hold_min": 3.8,
        "ts": 1781909022
      }
    ],
    "log_tail": [
      "[22:50:43] [t=25.9min] [SCANNER] +53 candidatos (fila=53)\n",
      "[22:50:49] [t=26.0min] [STATUS] posicoes=0 | trades=5 | wins=1 losses=4 | pnl=-0.17751SOL\n",
      "[22:50:58] [t=26.2min] [SCANNER] +53 candidatos (fila=53)\n",
      "[22:51:13] [t=26.4min] [SCANNER] +53 candidatos (fila=53)\n",
      "[22:51:28] [t=26.7min] [SCANNER] +52 candidatos (fila=52)\n",
      "[22:51:43] [t=26.9min] [SCANNER] +52 candidatos (fila=52)\n",
      "[22:51:58] [t=27.2min] [SCANNER] +53 candidatos (fila=53)\n",
      "[22:52:13] [t=27.4min] [SCANNER] +53 candidatos (fila=53)\n",
      "[22:52:28] [t=27.7min] [SCANNER] +53 candidatos (fila=53)\n",
      "[22:52:44] [t=27.9min] [SCANNER] +53 candidatos (fila=53)\n",
      "[22:52:49] [t=28.0min] [STATUS] posicoes=0 | trades=5 | wins=1 losses=4 | pnl=-0.17751SOL\n",
      "[22:52:59] [t=28.2min] [SCANNER] +53 candidatos (fila=53)\n",
      "[22:53:14] [t=28.4min] [SCANNER] +53 candidatos (fila=53)\n",
      "[22:53:29] [t=28.7min] [SCANNER] +53 candidatos (fila=53)\n",
      "[22:53:44] [t=28.9min] [SCANNER] +53 candidatos (fila=53)\n",
      "[22:53:59] [t=29.2min] [SCANNER] +53 candidatos (fila=53)\n",
      "[22:54:14] [t=29.4min] [SCANNER] +53 candidatos (fila=53)\n",
      "[22:54:29] [t=29.7min] [SCANNER] +53 candidatos (fila=53)\n",
      "[22:54:44] [t=29.9min] [SCANNER] +53 candidatos (fila=53)\n",
      "[22:54:44] [t=29.9min] [skip] Nasdog h1=+142% m5=+142% liq=$0 wh=280 sol5m=126.30 bot=0% | ['liq=$0<$5,000']\n"
    ]
  },
  "total_tokens": 52,
  "total_wallets": 293
}